LICENSE
MANIFEST.in
README.rst
setup.py
atrcopy/__init__.py
atrcopy/_metadata.py
atrcopy/_version.py
atrcopy/ataridos.py
atrcopy/cartridge.py
atrcopy/container.py
atrcopy/dcm.py
atrcopy/diskimages.py
atrcopy/dos33.py
atrcopy/dummy.py
atrcopy/errors.py
atrcopy/executables.py
atrcopy/fstbt.py
atrcopy/kboot.py
atrcopy/magic.py
atrcopy/mame.py
atrcopy/omnivore_loader.py
atrcopy/parsers.py
atrcopy/segments.py
atrcopy/signatures.py
atrcopy/spartados.py
atrcopy/standard_delivery.py
atrcopy/utils.py
atrcopy.egg-info/PKG-INFO
atrcopy.egg-info/SOURCES.txt
atrcopy.egg-info/dependency_links.txt
atrcopy.egg-info/entry_points.txt
atrcopy.egg-info/requires.txt
atrcopy.egg-info/top_level.txt
atrcopy/templates/dos2dd.atr
atrcopy/templates/dos2dd.atr.inf
atrcopy/templates/dos2ed+2.5.atr
atrcopy/templates/dos2ed+2.5.atr.inf
atrcopy/templates/dos2ed.atr
atrcopy/templates/dos2ed.atr.inf
atrcopy/templates/dos2sd+2.0s.atr
atrcopy/templates/dos2sd+2.0s.atr.inf
atrcopy/templates/dos2sd.atr
atrcopy/templates/dos2sd.atr.inf
atrcopy/templates/dos33.dsk
atrcopy/templates/dos33.dsk.inf
atrcopy/templates/dos33autobrun.dsk
atrcopy/templates/dos33autobrun.dsk.inf
scripts/atrcopy
scripts/atrcopy.bat
test/test_add_file.py
test/test_ataridos.py
test/test_cart.py
test/test_container.py
test/test_create.py
test/test_jsonpickle.py
test/test_kboot.py
test/test_segment.py
test/test_serialize.py
test/test_utils.py
test_data/air_defense_v18.xex
test_data/container_dos_dd_test1.atr.bz2
test_data/container_dos_dd_test1.atr.gz
test_data/container_dos_dd_test1.atr.xz
test_data/container_dos_ed_test1.atr.bz2
test_data/container_dos_ed_test1.atr.gz
test_data/container_dos_ed_test1.atr.xz
test_data/container_dos_sd_test1.atr.bz2
test_data/container_dos_sd_test1.atr.gz
test_data/container_dos_sd_test1.atr.xz
test_data/create_binary.py
test_data/dos_dd_test1.atr
test_data/dos_dd_test2.atr
test_data/dos_dd_test3.atr
test_data/dos_dd_test4.atr
test_data/dos_dd_test5.atr
test_data/dos_ed_test1.atr
test_data/dos_ed_test2.atr
test_data/dos_ed_test3.atr
test_data/dos_ed_test4.atr
test_data/dos_ed_test5.atr
test_data/dos_sd_test1.atr
test_data/dos_sd_test2.atr
test_data/dos_sd_test3.atr
