Metadata-Version: 1.2
Name: atrcopy
Version: 10.1
Summary: Utility to manage file systems on Atari 8-bit (DOS 2) and Apple ][ (DOS 3.3) disk images.
Home-page: https://github.com/robmcmullen/atrcopy
Author: Rob McMullen
Author-email: feedback@playermissile.com
License: MPL 2.0
Platform: UNKNOWN
Classifier: Programming Language :: Python :: 3.6
Classifier: Intended Audience :: Developers
Classifier: License :: OSI Approved :: Mozilla Public License 2.0 (MPL 2.0)
Classifier: Topic :: Software Development :: Libraries
Classifier: Topic :: Utilities
Requires-Python: >=3.6
